Metadata-Version: 2.1
Name: odoo14-addon-mrp-multi-level
Version: 14.0.1.15.0
Summary: Adds an MRP Scheduler
Home-page: https://github.com/OCA/manufacture
Author: Ucamco, ForgeFlow, Odoo Community Association (OCA)
Author-email: support@odoo-community.org
License: LGPL-3
Platform: UNKNOWN
Classifier: Programming Language :: Python
Classifier: Framework :: Odoo
Classifier: Framework :: Odoo :: 14.0
Classifier: License :: OSI Approved :: GNU Lesser General Public License v3 (LGPLv3)
Classifier: Development Status :: 5 - Production/Stable
Requires-Python: >=3.6
Requires-Dist: odoo14-addon-mrp-warehouse-calendar
Requires-Dist: odoo <14.1dev,>=14.0a
